odoo/addons/survey_partner_representative/README.rst
odoo/addons/survey_partner_representative/__init__.py
odoo/addons/survey_partner_representative/__manifest__.py
odoo/addons/survey_partner_representative/controllers/__init__.py
odoo/addons/survey_partner_representative/controllers/main.py
odoo/addons/survey_partner_representative/demo/survey_partner_representative_demo.xml
odoo/addons/survey_partner_representative/i18n/es.po
odoo/addons/survey_partner_representative/i18n/it.po
odoo/addons/survey_partner_representative/i18n/survey_partner_representative.pot
odoo/addons/survey_partner_representative/models/__init__.py
odoo/addons/survey_partner_representative/models/survey_representative_mixin.py
odoo/addons/survey_partner_representative/models/survey_survey.py
odoo/addons/survey_partner_representative/models/survey_user_input.py
odoo/addons/survey_partner_representative/readme/CONFIGURE.md
odoo/addons/survey_partner_representative/readme/CONTEXT.md
odoo/addons/survey_partner_representative/readme/CONTRIBUTORS.md
odoo/addons/survey_partner_representative/readme/DESCRIPTION.md
odoo/addons/survey_partner_representative/readme/USAGE.md
odoo/addons/survey_partner_representative/security/survey_partner_representative_security.xml
odoo/addons/survey_partner_representative/static/description/icon.png
odoo/addons/survey_partner_representative/static/description/index.html
odoo/addons/survey_partner_representative/static/tests/survey_representative_tour.esm.js
odoo/addons/survey_partner_representative/tests/__init__.py
odoo/addons/survey_partner_representative/tests/models.py
odoo/addons/survey_partner_representative/tests/test_survey_partner_representative.py
odoo/addons/survey_partner_representative/tests/test_survey_representative_mixin.py
odoo/addons/survey_partner_representative/views/survey_survey_views.xml
odoo/addons/survey_partner_representative/views/survey_user_input_views.xml
odoo_addon_survey_partner_representative-17.0.1.0.0.5.dist-info/METADATA
odoo_addon_survey_partner_representative-17.0.1.0.0.5.dist-info/WHEEL
odoo_addon_survey_partner_representative-17.0.1.0.0.5.dist-info/top_level.txt
odoo_addon_survey_partner_representative-17.0.1.0.0.5.dist-info/RECORD
